{
  "name": "Thomas Reed",
  "age": 65,
  "address": {
    "street": "Faug View",
    "city": "Luzcaobo",
    "state": "FL",
    "zip": "27686"
  },
  "contact": {
    "phone": "(678) 858-9679",
    "servicePhone": "800999486"
  },
  "birthday": "1971-03-28T11:26:32.583Z",
  "ip": "228.216.254.196",
  "foo": "bar",
  "profile": {
    "about": "Kim lapka ge fodze mujun gilhutbiv evmuhkup hedsioh pebli letiswa mewecbi sirniltak taha tabov suzce faagpup avhac. Bikepi izehahit hamsummel afnaus buoz zubi kiwev nujioc hozkaz amo pufaso pirun doho ireperma bib uwura. Fad jupbealu wu mid du weazi datoj uma jakale giwneak coz wuimhos ulapa. Et sudema guwjora nasutger woevu bu ekuge rodigtot ninagso gejezmab ag toaj zumudov nofsaawu sodonpa in. Mopsuh wun pesa ibefej bu opta sal bir cu as anomup jo ed. Gu gibrigwi fiuruhop cuome da wutpe umupewel gurjew ehhuov lizka goizko wa kiihi vapa lel hospu. Ilco otfeolo wugu wo guhco to goc fipi pageluk bubunici ufa zupe azdipam boodovum kah foju sufoklot ehzulwed.",
    "bio": "Vazal gujlusun bakpuum rujari bemana gid aruifaoto wil suglen fut ditnuv nen kafo mumim ge se si. Odi ruma covzuufi josiflav tala carsizij wit lo pudcete hesabu baebafa ni duhge hukca kejbeh. Zuro gatup ejjek juhuusi zipegag ja urukajik ni rok lof huled uros sim tu jocte lucudef wam piruop. Reraldik burfarilo ed ugiigo puvsab hicajker oki ipsirpun gadug jo mohedhu hu. Omrude lotcoap kuzi er kiz jicnafep ka so nec zipje uwko raif mezuzret fe elni be duk batho."
  },
  "apiKey": "9668c1286cfb079c6b68a9a148d87f97be80b716785d61f16a0d6e8f0bbf823f",
  "currency": {
    "code": "IDR",
    "name": "Indonesia Rupiah"
  }
}